tests/data/__init__.py
tests/data/snake_oil_data.py
tests/data/spe1_st/field_properties.tmpl
tests/data/spe1_st/field_properties_priors
tests/data/spe1_st/obs.txt
tests/data/spe1_st/spe1.ert
tests/data/spe1_st/resources/SPE1CASE2.DATA.jinja2
tests/data/spe1_st/resources/refcase/SPE1CASE2.SMSPEC
tests/data/spe1_st/resources/refcase/SPE1CASE2.UNSMRY
tests/data/spe1_st/tests/conftest.py
tests/data/spe1_st/tests/test_webviz_ert.py
webviz_ert/__init__.py
webviz_ert/__main__.py
webviz_ert/assets/__init__.py
webviz_ert/assets/bootstrap-grid.css
webviz_ert/assets/bootstrap.min.css
webviz_ert/assets/ert-style.css
webviz_ert/assets/ert-style.json
webviz_ert/assets/webviz-config.yml
webviz_ert/controllers/__init__.py
webviz_ert/controllers/controller_functions.py
webviz_ert/controllers/element_dropdown_controller.py
webviz_ert/controllers/ensemble_selector_controller.py
webviz_ert/controllers/multi_parameter_controller.py
webviz_ert/controllers/multi_response_controller.py
webviz_ert/controllers/observation_response_controller.py
webviz_ert/controllers/parameter_comparison_controller.py
webviz_ert/controllers/parameter_selector_controller.py
webviz_ert/controllers/plot_view_controller.py
webviz_ert/controllers/response_correlation_controller.py
webviz_ert/data_loader/__init__.py
webviz_ert/models/__init__.py
webviz_ert/models/data_model.py
webviz_ert/models/ensemble_model.py
webviz_ert/models/observation.py
webviz_ert/models/parameter_model.py
webviz_ert/models/plot_model.py
webviz_ert/models/realization.py
webviz_ert/models/response.py
webviz_ert/plugins/__init__.py
webviz_ert/plugins/_observation_analyzer.py
webviz_ert/plugins/_parameter_comparison.py
webviz_ert/plugins/_response_comparison.py
webviz_ert/plugins/_response_correlation.py
webviz_ert/plugins/_webviz_ert.py
webviz_ert/views/__init__.py
webviz_ert/views/correlation_view.py
webviz_ert/views/element_dropdown_view.py
webviz_ert/views/ensemble_selector_view.py
webviz_ert/views/misfit_view.py
webviz_ert-0.7.0.dist-info/licenses/LICENSE
webviz_ert-0.7.0.dist-info/METADATA
webviz_ert-0.7.0.dist-info/WHEEL
webviz_ert-0.7.0.dist-info/entry_points.txt
webviz_ert-0.7.0.dist-info/top_level.txt
webviz_ert-0.7.0.dist-info/RECORD
