Metadata-Version: 2.4
Name: webviz-ert
Version: 0.7.0
Summary: Webviz plugins for ERT
Author: Equinor
Classifier: Natural Language :: English
Classifier: Environment :: Web Environment
Classifier: Framework :: Dash
Classifier: Framework :: Flask
Classifier: Topic :: Scientific/Engineering
Classifier: Intended Audience :: Science/Research
Classifier: Programming Language :: Python
Classifier: Programming Language :: Python :: 3
Classifier: License :: OSI Approved :: GNU Lesser General Public License v3 (LGPLv3)
License-File: LICENSE
Requires-Dist: dash-bootstrap-components
Requires-Dist: dash-daq
Requires-Dist: dash<3.0.0
Requires-Dist: pandas
Requires-Dist: requests
Requires-Dist: webviz-config-equinor
Requires-Dist: webviz-config>=0.0.40
Requires-Dist: webviz-subsurface-components
Dynamic: author
Dynamic: classifier
Dynamic: description
Dynamic: description-content-type
Dynamic: license-file
Dynamic: requires-dist
Dynamic: summary
